JingtongGoMasteringGoZhongwenban/README.md
JingtongGoMasteringGoZhongwenban/__init__.py
JingtongGoMasteringGoZhongwenban/__main__.py
JingtongGoMasteringGoZhongwenban/file.epub
JingtongGoMasteringGoZhongwenban/index.html
JingtongGoMasteringGoZhongwenban/css/__init__.py
JingtongGoMasteringGoZhongwenban/css/annotations.css
JingtongGoMasteringGoZhongwenban/css/main.css
JingtongGoMasteringGoZhongwenban/css/normalize.css
JingtongGoMasteringGoZhongwenban/css/popup.css
JingtongGoMasteringGoZhongwenban/font/__init__.py
JingtongGoMasteringGoZhongwenban/font/fontello.eot
JingtongGoMasteringGoZhongwenban/font/fontello.svg
JingtongGoMasteringGoZhongwenban/font/fontello.ttf
JingtongGoMasteringGoZhongwenban/font/fontello.woff
JingtongGoMasteringGoZhongwenban/img/__init__.py
JingtongGoMasteringGoZhongwenban/img/annotator-glyph-sprite.png
JingtongGoMasteringGoZhongwenban/img/annotator-icon-sprite.png
JingtongGoMasteringGoZhongwenban/img/apple-touch-icon.png
JingtongGoMasteringGoZhongwenban/img/cancelfullscreen.png
JingtongGoMasteringGoZhongwenban/img/close.png
JingtongGoMasteringGoZhongwenban/img/fullscreen.png
JingtongGoMasteringGoZhongwenban/img/loader.gif
JingtongGoMasteringGoZhongwenban/img/menu-icon.png
JingtongGoMasteringGoZhongwenban/img/save.png
JingtongGoMasteringGoZhongwenban/img/saved.png
JingtongGoMasteringGoZhongwenban/img/settings-s.png
JingtongGoMasteringGoZhongwenban/img/settings.png
JingtongGoMasteringGoZhongwenban/img/star.png
JingtongGoMasteringGoZhongwenban/js/__init__.py
JingtongGoMasteringGoZhongwenban/js/epub.js
JingtongGoMasteringGoZhongwenban/js/epub.min.js
JingtongGoMasteringGoZhongwenban/js/epub.min.map
JingtongGoMasteringGoZhongwenban/js/hooks.min.js
JingtongGoMasteringGoZhongwenban/js/hooks.min.map
JingtongGoMasteringGoZhongwenban/js/reader.js
JingtongGoMasteringGoZhongwenban/js/reader.js.map
JingtongGoMasteringGoZhongwenban/js/reader.min.js
JingtongGoMasteringGoZhongwenban/js/reader.min.map
JingtongGoMasteringGoZhongwenban/js/hooks/__init__.py
jingtong_go_mastering_go_zhongwenban-2024.3.4.0.dist-info/METADATA
jingtong_go_mastering_go_zhongwenban-2024.3.4.0.dist-info/WHEEL
jingtong_go_mastering_go_zhongwenban-2024.3.4.0.dist-info/entry_points.txt
jingtong_go_mastering_go_zhongwenban-2024.3.4.0.dist-info/top_level.txt
jingtong_go_mastering_go_zhongwenban-2024.3.4.0.dist-info/RECORD
